edu_card_models/BaseSheet.py
edu_card_models/SheetCR1.py
edu_card_models/SheetCR2.py
edu_card_models/SheetCR2ROIs.py
edu_card_models/SheetV1.py
edu_card_models/__init__.py
edu_card_utils/ImageIntelligence.py
edu_card_utils/ImageManipulation.py
edu_card_utils/OpenCVUtils.py
edu_card_utils/__init__.py
edu_card_utils/constants.py
edu_card_utils/coordutils.py
edu_card_utils/cvutils.py
edu_nibble_code/NibbleReader.py
edu_nibble_code/__init__.py
edu_card_analyser-1.4.1.dist-info/METADATA
edu_card_analyser-1.4.1.dist-info/WHEEL
edu_card_analyser-1.4.1.dist-info/top_level.txt
edu_card_analyser-1.4.1.dist-info/RECORD
