Metadata-Version: 2.1
Name: edu-card-analyser
Version: 1.4.1
Summary: Educatena's Computer Vision python package for analysing Answer Cards from images.
Home-page: https://github.com/educatena/edu-card-analyser
Author: Educatena
Author-email: tic@educatena.com.br
License: UNKNOWN
Platform: UNKNOWN
Classifier: Programming Language :: Python :: 3
Classifier: Operating System :: OS Independent
Requires-Python: >=3.6
